sprinkles/__init__.py
sprinkles/_secrets.py
sprinkles/_templating.py
sprinkles/commands.py
sprinkles_config-0.1.4.dist-info/entry_points.txt
sprinkles_config-0.1.4.dist-info/LICENSE
sprinkles_config-0.1.4.dist-info/WHEEL
sprinkles_config-0.1.4.dist-info/METADATA
sprinkles_config-0.1.4.dist-info/RECORD
