Metadata-Version: 2.1
Name: sprinkles-config
Version: 0.1.4
Summary: Generate config files from AWS Secrets
Home-page: https://github.com/okal/sprinkles
License: MIT
Author: Okal Otieno
Author-email: okal@justokal.com
Requires-Python: >=3.6,<4.0
Classifier: License :: OSI Approved :: MIT License
Classifier: Programming Language :: Python :: 3
Classifier: Programming Language :: Python :: 3.6
Classifier: Programming Language :: Python :: 3.7
Classifier: Programming Language :: Python :: 3.8
Requires-Dist: Jinja2
Requires-Dist: boto3
Requires-Dist: click
Requires-Dist: tomlkit
